LICENSE
MANIFEST.in
README.md
pyproject.toml
webuse/__init__.py
webuse/__main__.py
webuse/api.py
webuse/engine.py
webuse.egg-info/PKG-INFO
webuse.egg-info/SOURCES.txt
webuse.egg-info/dependency_links.txt
webuse.egg-info/requires.txt
webuse.egg-info/top_level.txt