Metadata-Version: 2.4
Name: webuse
Version: 0.0.1
Summary: Minimal browser for performing web-based actions on your command.
Author-email: lexiforest <kongyifei@gmail.com>
License: MIT License
Project-URL: repository, https://github.com/lexiforest/webuse
Classifier: Development Status :: 4 - Beta
Classifier: Intended Audience :: Developers
Classifier: License :: OSI Approved :: MIT License
Classifier: Programming Language :: Python :: 3
Classifier: Programming Language :: Python :: 3.9
Classifier: Programming Language :: Python :: 3.10
Classifier: Programming Language :: Python :: 3.11
Classifier: Programming Language :: Python :: 3.12
Classifier: Programming Language :: Python :: 3.13
Requires-Python: >=3.9
License-File: LICENSE
Requires-Dist: pyside6
Requires-Dist: qasync
Requires-Dist: setproctitle
Requires-Dist: aiohttp
Provides-Extra: dev
Provides-Extra: build
Requires-Dist: cibuildwheel; extra == "build"
Requires-Dist: wheel; extra == "build"
Provides-Extra: test
Dynamic: license-file
